{
  "stories": [
    {
      "id": 1,
      "content": "Overheard at a café in Stockholm: Someone claimed they'd seen a moose casually strolling in Gamla Stan!",
      "createdAt": "2023-12-10T07:30:00Z",
      "location": { "latitude": 59.3293, "longitude": 18.0686 },
      "city": "Stockholm",
      "ranking": 5
    },
    {
      "id": 2,
      "content": "A local in Gothenburg swore they spotted a submarine surfacing near the archipelago. Could it be true?",
      "createdAt": "2023-12-09T15:45:00Z",
      "location": { "latitude": 57.7089, "longitude": 11.9746 },
      "city": "Gothenburg",
      "ranking": 4
    },
    {
      "id": 3,
      "content": "Rumor has it that a famous Hollywood star was seen buying kanelbullar at a bakery in Malmö!",
      "createdAt": "2023-12-08T22:00:00Z",
      "location": { "latitude": 55.604981, "longitude": 13.003822 },
      "city": "Malmö",
      "ranking": 4
    },
    {
      "id": 4,
      "content": "Did you hear about the Uppsala student who allegedly invented a new language just for their thesis?",
      "createdAt": "2023-12-07T10:30:00Z",
      "location": { "latitude": 59.8586, "longitude": 17.6389 },
      "city": "Uppsala",
      "ranking": 5
    },
    {
      "id": 5,
      "content": "A group in Umeå claimed they found a hidden treasure map in an old book at the city library.",
      "createdAt": "2023-12-06T03:15:00Z",
      "location": { "latitude": 63.8258, "longitude": 20.263 },
      "city": "Umeå",
      "ranking": 5
    },
    {
      "id": 6,
      "content": "Locals in Lund were baffled by a mysterious cat that only appears during full moons to play the piano in a window.",
      "createdAt": "2023-12-05T19:00:00Z",
      "location": { "latitude": 55.7047, "longitude": 13.191 },
      "city": "Lund",
      "ranking": 3
    },
    {
      "id": 7,
      "content": "A fisherman in Helsingborg insists he caught a fish that could speak three languages!",
      "createdAt": "2023-12-04T14:25:00Z",
      "location": { "latitude": 56.0465, "longitude": 12.6945 },
      "city": "Helsingborg",
      "ranking": 4
    },
    {
      "id": 8,
      "content": "A mysterious figure in a cloak was seen performing magic tricks on the streets of Västerås.",
      "createdAt": "2023-12-03T22:10:00Z",
      "location": { "latitude": 59.6099, "longitude": 16.5448 },
      "city": "Västerås",
      "ranking": 2
    },
    {
      "id": 9,
      "content": "Residents of Örebro talk about a secret underground city only accessible through hidden passages in the castle.",
      "createdAt": "2023-12-02T08:00:00Z",
      "location": { "latitude": 59.2753, "longitude": 15.2134 },
      "city": "Örebro",
      "ranking": 5
    },
    {
      "id": 10,
      "content": "In Linköping, there's a tale of a ghostly cyclist who rides through the main square at midnight.",
      "createdAt": "2023-12-01T11:30:00Z",
      "location": { "latitude": 58.4108, "longitude": 15.6214 },
      "city": "Linköping",
      "ranking": 3
    }
  ]
}
